odoo10_addon_web_x2many_delete_all-10.0.1.0.0-py2.7-nspkg.pth
odoo10_addon_web_x2many_delete_all-10.0.1.0.0.dist-info/top_level.txt
odoo10_addon_web_x2many_delete_all-10.0.1.0.0.dist-info/WHEEL
odoo10_addon_web_x2many_delete_all-10.0.1.0.0.dist-info/RECORD
odoo10_addon_web_x2many_delete_all-10.0.1.0.0.dist-info/metadata.json
odoo10_addon_web_x2many_delete_all-10.0.1.0.0.dist-info/DESCRIPTION.rst
odoo10_addon_web_x2many_delete_all-10.0.1.0.0.dist-info/METADATA
odoo10_addon_web_x2many_delete_all-10.0.1.0.0.dist-info/namespace_packages.txt
odoo/addons/web_x2many_delete_all/__manifest__.py
odoo/addons/web_x2many_delete_all/__init__.py
odoo/addons/web_x2many_delete_all/README.rst
odoo/addons/web_x2many_delete_all/templates/assets.xml
odoo/addons/web_x2many_delete_all/static/src/js/web_x2many_delete_all.js
odoo/addons/web_x2many_delete_all/static/src/css/web_x2many_delete_all.css
odoo/addons/web_x2many_delete_all/static/src/xml/web_x2many_delete_all.xml
